Extendedmathuse/__init__.py
Extendedmathuse-2.1.2.dist-info/LICENSE
Extendedmathuse-2.1.2.dist-info/METADATA
Extendedmathuse-2.1.2.dist-info/WHEEL
Extendedmathuse-2.1.2.dist-info/top_level.txt
Extendedmathuse-2.1.2.dist-info/RECORD
