Metadata-Version: 2.1
Name: Extendedmathuse
Version: 2.1.2
Summary: Simple digital manipulation
Home-page: https://pypi.org
Author: Tang Jiawei
Author-email: 3245813583@qq.com
License: UNKNOWN
Platform: UNKNOWN
Classifier: Programming Language :: Python :: 3
Classifier: License :: OSI Approved :: MIT License
Classifier: Operating System :: OS Independent
Requires-Python: >=3.6
